bitvectorset/__init__.py
bitvectorset/bitvectorset.py
bitvectorset-1.0.2.dist-info/METADATA
bitvectorset-1.0.2.dist-info/WHEEL
bitvectorset-1.0.2.dist-info/licenses/LICENSE
bitvectorset-1.0.2.dist-info/RECORD
