Metadata-Version: 2.4
Name: bitvectorset
Version: 1.0.2
Summary: Efficient immutable sets as bit-vectors
Project-URL: Homepage, https://github.com/pPomCo/py-bitvectorset
Author-email: Pierre Pomeret-Coquot <pierre.pomeret@irit.fr>
License-Expression: MIT
License-File: LICENSE
Classifier: Operating System :: OS Independent
Classifier: Programming Language :: Python :: 3
Requires-Python: >=3
